debugme.py
debugme-1.10.dist-info/COPYING
debugme-1.10.dist-info/METADATA
debugme-1.10.dist-info/WHEEL
debugme-1.10.dist-info/top_level.txt
debugme-1.10.dist-info/RECORD
