Metadata-Version: 2.1
Name: debugme
Version: 1.10
Summary: Interactive terminal for inspecting the running state of a python program
Home-page: http://github.com/seveas/debugme
Author: Dennis Kaarsemaker
Author-email: dennis@kaarsemaker.net
License: zlib
Platform: UNKNOWN
Classifier: Development Status :: 5 - Production/Stable
Classifier: Intended Audience :: Developers
Classifier: License :: OSI Approved :: zlib/libpng License
Classifier: Programming Language :: Python
Classifier: Programming Language :: Python :: 3
Classifier: Topic :: Software Development :: Libraries :: Python Modules
